leaflet_admin_list/__init__.py
leaflet_admin_list/admin.py
leaflet_admin_list/filters.py
leaflet_admin_list/version.py
leaflet_admin_list/templates/leaflet_admin_list/leaflet_admin_filter.html
leaflet_admin_list/templates/leaflet_admin_list/leaflet_admin_list.html
django_leaflet_admin_list-0.0.9.dist-info/LICENSE
django_leaflet_admin_list-0.0.9.dist-info/METADATA
django_leaflet_admin_list-0.0.9.dist-info/WHEEL
django_leaflet_admin_list-0.0.9.dist-info/top_level.txt
django_leaflet_admin_list-0.0.9.dist-info/RECORD
