Metadata-Version: 2.1
Name: django-leaflet-admin-list
Version: 0.0.9
Summary: Django Leaflet Admin List
Home-page: https://github.com/nnseva/django-leaflet-admin-list
Author: Vsevolod Novikov
Author-email: nnseva@gmail.com
License: LGPL
Keywords: django admin leaflet map list view
Classifier: Programming Language :: Python
Classifier: Topic :: Software Development :: Libraries :: Python Modules
Classifier: Development Status :: 4 - Beta
Classifier: Framework :: Django
Classifier: Framework :: Django :: 2.0
Classifier: Framework :: Django :: 2.1
Classifier: Framework :: Django :: 2.2
Classifier: Framework :: Django :: 3.0
Classifier: Framework :: Django :: 3.1
Classifier: Framework :: Django :: 3.2
Classifier: Programming Language :: Python :: 3.6
Classifier: Programming Language :: Python :: 3.7
Classifier: Programming Language :: Python :: 3.8
Classifier: Programming Language :: Python :: 3.9
Classifier: License :: OSI Approved :: GNU Library or Lesser General Public License (LGPL)
License-File: LICENSE
Requires-Dist: django
Requires-Dist: django-leaflet
